[{"Ganador":{"Caracteristicas1":{"Velocidad":3,"Destreza":2,"Fuerza":3,"Armadura":7,"Salud":100,"Nivelfuria":1,"Pociondevida":1},"Datos1":{"Name":"Sejuani","Region":"Freljord","Tipoclase":"Luchador","Frase":"CONGELATE!!!"}},"Perdedor":{"Caracteristicas1":{"Velocidad":6,"Destreza":1,"Fuerza":6,"Armadura":3,"Salud":0,"Nivelfuria":3,"Pociondevida":18},"Datos1":{"Name":"Ashe","Region":"Freljord","Tipoclase":"Tirador","Frase":"FUEGO A DISCRECION!!!"}},"Informacion":"Sejuani ES EL GANADOR"},{"Ganador":{"Caracteristicas1":{"Velocidad":6,"Destreza":8,"Fuerza":2,"Armadura":4,"Salud":78,"Nivelfuria":2,"Pociondevida":18},"Datos1":{"Name":"RekSai","Region":"Vacio","Tipoclase":"Luchador","Frase":"*Rugidos y ruidos extranios*"}},"Perdedor":{"Caracteristicas1":{"Velocidad":3,"Destreza":2,"Fuerza":3,"Armadura":7,"Salud":0,"Nivelfuria":3,"Pociondevida":3},"Datos1":{"Name":"Sejuani","Region":"Freljord","Tipoclase":"Luchador","Frase":"CONGELATE!!!"}},"Informacion":"RekSai TE HA DERROTADO"}]
